{"entity_title":"Aqrab al-mawārid fī fuṣuḥ al-ʻArabīyah wa-al-shawārid","identifier":"columbia_aco000132","entity_path":"http://stage-dl-pa.home.nyu.edu/books/books/columbia_aco000132/1","base_url":"http://stage-dl-pa.home.nyu.edu/books/","entity_language":"en","entity_status":"1","entity_type":"dlts_book","metadata":{"author":{"label":"Author/Contributor","value":["Shartūnī, Saʻīd al-Khūrī, 1849-1912"],"field_type":"text_textfield","machine_name":"field_author"},"binding_orientation":{"label":"Binding Orientation","value":["Vertical"],"field_type":"options_buttons","machine_name":"field_binding_orientation"},"call_number":{"label":"Call Number","value":["PJ6622 .S54 1982"],"field_type":"text_textfield","machine_name":"field_call_number"},"collection":{"label":"Collection","value":[{"title":"Arabic Collections Online","type":"dlts_collection","language":"und","identifier":"f88f5562-2152-41a7-979f-86a6fb4149aa","code":"aco","name":"Arabic Collections Online","partner":{"title":"Columbia University Libraries","type":"dlts_partner","language":"und","identifier":"1610d763-a788-42fe-996a-f8717403e7e3","code":"columbia","name":"Columbia University Libraries"}}],"field_type":"node_reference_autocomplete","machine_name":"field_collection"},"contributor":{"label":"Contributor","value":[],"field_type":"text_textfield","machine_name":"field_contributor"},"creator":{"label":"Creator","value":[],"field_type":"text_textfield","machine_name":"field_creator"},"description":{"label":"Description","value":[],"field_type":"text_textfield","machine_name":"field_description"},"dimensions":{"label":"Dimensions","value":[],"field_type":"text_textfield","machine_name":"field_dimensions"},"editor":{"label":"Editor","value":[],"field_type":"text_textfield","machine_name":"field_editor"},"handle":{"label":"Permanent Link","value":["http://hdl.handle.net/2333.1/kkwh7332"],"field_type":"link_field","machine_name":"field_handle"},"identifier":{"label":"Identifier","value":["columbia_aco000132"],"field_type":"text_textfield","machine_name":"field_identifier"},"isbn":{"label":"ISBN","value":[],"field_type":"text_textfield","machine_name":"field_isbn"},"language":{"label":"Language","value":["Arabic"],"field_type":"text_textfield","machine_name":"field_language"},"language_code":{"label":"Language Code","value":["ara"],"field_type":"text_textfield","machine_name":"field_language_code"},"number":{"label":"Number","value":[],"field_type":"text_textfield","machine_name":"field_number"},"ocr_text":{"label":"OCR Text","value":[],"field_type":"file_generic","machine_name":"field_ocr_text"},"other_version":{"label":"Other Version","value":[],"field_type":"link_field","machine_name":"field_other_version"},"page_count":{"label":"Page Count","value":["564"],"field_type":"number","machine_name":"field_page_count"},"pdf_file":{"label":"PDF","value":[{"fid":"403716","uid":"1","filename":"columbia_aco000132_hi.pdf","uri":"public://columbia_aco000132/columbia_aco000132_hi.pdf","filemime":"application/pdf","filesize":"377236448","status":"1","timestamp":"1421830477","uuid":"45653124-a70d-443e-9775-e7caf41c4fee","rdf_mapping":[],"display":"1","description":"","fileserver":"fileserver://books/columbia_aco000132/columbia_aco000132_hi.pdf"},{"fid":"403717","uid":"1","filename":"columbia_aco000132_lo.pdf","uri":"public://columbia_aco000132/columbia_aco000132_lo.pdf","filemime":"application/pdf","filesize":"66476936","status":"1","timestamp":"1421830478","uuid":"89e3a4d2-bff8-412e-a01a-d20369710ee0","rdf_mapping":[],"display":"1","description":"","fileserver":"fileserver://books/columbia_aco000132/columbia_aco000132_lo.pdf"}],"field_type":"file_generic","machine_name":"field_pdf_file"},"publication_date":{"label":"Date of Publication","value":[],"field_type":"date_text","machine_name":"field_publication_date"},"publication_location":{"label":"Place of Publication","value":["Qum, Īrān"],"field_type":"text_textfield","machine_name":"field_publication_location"},"publisher":{"label":"Publisher","value":["Manshūrāt Maktabat Āyat Allāh al-ʻUẓmá al-Marʻashī al-Najafī"],"field_type":"text_textfield","machine_name":"field_publisher"},"read_order":{"label":"Read Order","value":["Right to left"],"field_type":"options_buttons","machine_name":"field_read_order"},"representative_image":{"label":"Representative Image","value":{"fid":"403718","uid":"1","filename":"columbia_aco000132_thumb.jpg","uri":"public://columbia_aco000132/columbia_aco000132_thumb.jpg","filemime":"image/jpeg","filesize":"94197","status":"1","timestamp":"1421830479","uuid":"6ba1ba7e-1f24-486e-9aaf-3fb83d9c1fdf","rdf_mapping":[],"alt":"","title":"","width":"527","height":"720","fileserver":"fileserver://books/columbia_aco000132/columbia_aco000132_thumb.jpg"},"field_type":"image_image","machine_name":"field_representative_image"},"rights":{"label":"Rights","value":["\n    NYU believes the materials displayed on this site are all in the\n    public domain. However, if you believe that you are the\n    copyright owner of any material displayed here, please see our\n    takedown policy: http://dlib.nyu.edu/aco/takedownpolicy/\n  "],"field_type":"text_textarea","machine_name":"field_rights"},"scan_date":{"label":"Scan Date","value":[],"field_type":"date_text","machine_name":"field_scan_date"},"scan_order":{"label":"Scan Order","value":["Left to right"],"field_type":"options_buttons","machine_name":"field_scan_order"},"scanning_notes":{"label":"Scanning Notes","value":[],"field_type":"text_textarea","machine_name":"field_scanning_notes"},"sequence_count":{"label":"Sequence Count","value":["564"],"field_type":"number","machine_name":"field_sequence_count"},"subject":{"label":"Subject","value":["Arabic language -- Dictionaries","Arabic language"],"field_type":"taxonomy_autocomplete","machine_name":"field_subject"},"subtitle":{"label":"Subtitle","value":[],"field_type":"text_textfield","machine_name":"field_subtitle"},"title":{"label":"Title","value":["Aqrab al-mawārid fī fuṣuḥ al-ʻArabīyah wa-al-shawārid"],"field_type":"text_textfield","machine_name":"field_title"},"topic":{"label":"Topic","value":[],"field_type":"text_textfield","machine_name":"field_topic"},"volume":{"label":"Volume","value":[],"field_type":"text_textfield","machine_name":"field_volume"},"publication_date_text":{"label":"Date of Publication","value":["1403 [1982 or 1983]-1982"],"field_type":"text_textfield","machine_name":"field_publication_date_text"},"partner":{"label":"Provider","value":[{"title":"Columbia University Libraries","type":"dlts_partner","language":"und","identifier":"1610d763-a788-42fe-996a-f8717403e7e3","code":"columbia","name":"Columbia University Libraries"}],"field_type":"node_reference_autocomplete","machine_name":"field_partner"},"geographic_coordinates":{"label":"Geographic Coordinates","value":[],"field_type":"geolocation_text","machine_name":"field_geographic_coordinates"},"geographic_subject":{"label":"Geographic Subject","value":[],"field_type":"taxonomy_autocomplete","machine_name":"field_geographic_subject"}},"multivolume":{"volume":[{"identifier":"d596ca5d-67bd-4b9b-8a0f-8bc9f96660ec_columbia_aco000132","volume_number":"3","volume_number_str":"v.3","collection":[{"title":"Arabic Collections Online","type":"dlts_collection","language":"und","identifier":"f88f5562-2152-41a7-979f-86a6fb4149aa","code":"aco","name":"Arabic Collections Online","partner":{"title":"Columbia University Libraries","type":"dlts_partner","language":"und","identifier":"1610d763-a788-42fe-996a-f8717403e7e3","code":"columbia","name":"Columbia University Libraries"}}],"isPartOf":[{"title":"Multi-Volume d596ca5d-67bd-4b9b-8a0f-8bc9f96660ec","type":"dlts_multivol","language":"und","identifier":"d596ca5d-67bd-4b9b-8a0f-8bc9f96660ec","ri":null}]}]}}